aautils-3.0.dist-info/licenses/LICENSE
autils/data_structures.py
autils/archive/ar.py
autils/devel/astring.py
autils/devel/gdb.py
autils/devel/output.py
autils/devel/process.py
autils/devel/script.py
autils/devel/wait.py
autils/file/path.py
autils/network/__init__.py
autils/network/ports.py
autils_external/__init__.py
autils_external/gdbmi_parser.py
autils_external/spark.py
aautils-3.0.dist-info/METADATA
aautils-3.0.dist-info/WHEEL
aautils-3.0.dist-info/top_level.txt
aautils-3.0.dist-info/RECORD
