Metadata-Version: 2.4
Name: aautils
Version: 3.0
Summary: Utility Libraries to power your tests (or general applications)
Author-email: Cleber Rosa <crosa@redhat.com>, Harvey James Lynden <hlynden@redhat.com>, Jan Richter <jarichte@redhat.com>
Maintainer-email: Cleber Rosa <crosa@redhat.com>, Harvey James Lynden <hlynden@redhat.com>, Jan Richter <jarichte@redhat.com>
License:                     GNU GENERAL PUBLIC LICENSE
Project-URL: Homepage, https://avocado-framework.github.io/autils.html
Project-URL: Repository, https://github.com/avocado-framework/aautils
Keywords: Avocado,testing,utility,library,test
Classifier: Development Status :: 3 - Alpha
Classifier: Programming Language :: Python
Classifier: Intended Audience :: Developers
Classifier: License :: OSI Approved :: GNU General Public License v2 (GPLv2)
Classifier: Topic :: Software Development :: Testing
Requires-Python: >=3.7
License-File: LICENSE
Dynamic: license-file
